gnlpy/__init__.py
gnlpy/cgroupstats.py
gnlpy/ipvs.py
gnlpy/netlink.py
gnlpy/taskstats.py
gnlpy-0.1.2.dist-info/DESCRIPTION.rst
gnlpy-0.1.2.dist-info/METADATA
gnlpy-0.1.2.dist-info/RECORD
gnlpy-0.1.2.dist-info/WHEEL
gnlpy-0.1.2.dist-info/metadata.json
gnlpy-0.1.2.dist-info/top_level.txt
