Metadata-Version: 2.0
Name: gnlpy
Version: 0.1.2
Summary: Generic NetLink PYthon library
Home-page: http://github.com/facebook/gnlpy
Author: Alex Gartrell
Author-email: agartrell@fb.com
License: BSD+
Keywords: generic netlink library
Platform: UNKNOWN
Classifier: Intended Audience :: Developers
Classifier: License :: OSI Approved :: BSD License
Classifier: Operating System :: POSIX :: Linux
Classifier: Programming Language :: Python :: 2
Classifier: Programming Language :: Python :: 2.7
Classifier: Programming Language :: Python :: 3
